{
    "available_scenarios": [
        {
            "Town03": [
                {
                    "available_event_configurations": [
                        {
                            "transform": {
                                "pitch": "0",
                                "x": 231.4,
                                "y": 23.39,
                                "yaw": 91.0,
                                "z": 1.0
                            }
                        },
                        {
                            "transform": {
                                "pitch": "0.0",
                                "x": "234.5481719970703",
                                "y": "23.466564178466797",
                                "yaw": "91.3932113647461",
                                "z": "0.0"
                            }
                        },
                        {
                            "transform": {
                                "pitch": "0",
                                "x": 234.52,
                                "y": 23.65,
                                "yaw": 90.0,
                                "z": 1.0
                            }
                        },
                        {
                            "transform": {
                                "pitch": "0.0",
                                "x": "231.04473876953125",
                                "y": "23.565475463867188",
                                "yaw": "91.3932113647461",
                                "z": "0.0"
                            }
                        },
                        {
                            "transform": {
                                "pitch": "0",
                                "x": 200.43,
                                "y": 62.24,
                                "yaw": 359.0,
                                "z": 1.0
                            }
                        },
                        {
                            "transform": {
                                "pitch": "0",
                                "x": 239.96,
                                "y": 98.9,
                                "yaw": 271.0,
                                "z": 1.12
                            }
                        },
                        {
                            "transform": {
                                "pitch": "359.1035461425781",
                                "x": "243.21473693847656",
                                "y": "98.97915649414062",
                                "yaw": "271.3932189941406",
                                "z": "0.29888251423835754"
                            }
                        },
                        {
                            "transform": {
                                "pitch": "0",
                                "x": -46.1,
                                "y": -140.7,
                                "yaw": 180.0,
                                "z": 0.92
                            }
                        },
                        {
                            "transform": {
                                "pitch": "0",
                                "x": -74.68,
                                "y": -106.31,
                                "yaw": 270.0,
                                "z": 0.92
                            }
                        },
                        {
                            "transform": {
                                "pitch": "361.3090515136719",
                                "x": "-78.15487670898438",
                                "y": "-106.30052185058594",
                                "yaw": "269.84375",
                                "z": "-0.374824196100235"
                            }
                        },
                        {
                            "transform": {
                                "pitch": "0",
                                "x": -78.1,
                                "y": -106.31,
                                "yaw": 270.0,
                                "z": 0.92
                            }
                        },
                        {
                            "transform": {
                                "pitch": "361.3090515136719",
                                "x": "-74.6549072265625",
                                "y": "-106.31939697265625",
                                "yaw": "269.84375",
                                "z": "-0.3746110796928406"
                            }
                        },
                        {
                            "transform": {
                                "pitch": "0",
                                "x": -88.11,
                                "y": -170.3,
                                "yaw": 90.0,
                                "z": 0.92
                            }
                        },
                        {
                            "transform": {
                                "pitch": "0.0",
                                "x": "-84.04679870605469",
                                "y": "-170.06784057617188",
                                "yaw": "93.27017974853516",
                                "z": "0.0"
                            }
                        },
                        {
                            "transform": {
                                "pitch": "0",
                                "x": -84.48,
                                "y": -170.3,
                                "yaw": 91.0,
                                "z": 0.92
                            }
                        },
                        {
                            "transform": {
                                "pitch": "0.0",
                                "x": "-87.52928924560547",
                                "y": "-170.4742431640625",
                                "yaw": "93.27017974853516",
                                "z": "0.0"
                            }
                        },
                        {
                            "transform": {
                                "pitch": "0",
                                "x": -85.2,
                                "y": -28.87,
                                "yaw": 89.0,
                                "z": 1.3
                            }
                        },
                        {
                            "transform": {
                                "pitch": "0.8396051526069641",
                                "x": "-88.44371032714844",
                                "y": "-28.86114501953125",
                                "yaw": "89.84374237060547",
                                "z": "-0.26660484075546265"
                            }
                        },
                        {
                            "transform": {
                                "pitch": "0",
                                "x": -116.67,
                                "y": 0.32,
                                "yaw": 0.0,
                                "z": 1.3
                            }
                        },
                        {
                            "transform": {
                                "pitch": "0",
                                "x": -113.37,
                                "y": -135.68,
                                "yaw": 1.0,
                                "z": 2.7
                            }
                        },
                        {
                            "transform": {
                                "pitch": "0",
                                "x": -32.34,
                                "y": -135.1,
                                "yaw": 0.0,
                                "z": 1.0
                            }
                        },
                        {
                            "transform": {
                                "pitch": "0",
                                "x": 5.83,
                                "y": -104.82,
                                "yaw": 270.0,
                                "z": 1.0
                            }
                        },
                        {
                            "transform": {
                                "pitch": "0.0",
                                "x": "9.106517791748047",
                                "y": "-104.73915100097656",
                                "yaw": "-88.58646392822266",
                                "z": "0.0"
                            }
                        },
                        {
                            "transform": {
                                "pitch": "0",
                                "x": 9.33,
                                "y": -104.82,
                                "yaw": 270.0,
                                "z": 1.0
                            }
                        },
                        {
                            "transform": {
                                "pitch": "0.0",
                                "x": "5.609712600708008",
                                "y": "-104.91180419921875",
                                "yaw": "-88.58646392822266",
                                "z": "0.0"
                            }
                        },
                        {
                            "transform": {
                                "pitch": "354",
                                "x": 37.76,
                                "y": -137.76,
                                "yaw": 181.0,
                                "z": 3.73
                            }
                        },
                        {
                            "transform": {
                                "pitch": "0",
                                "x": 0.6,
                                "y": -167.82,
                                "yaw": 90.0,
                                "z": 1.0
                            }
                        },
                        {
                            "transform": {
                                "pitch": "360.0",
                                "x": "-3.3387670516967773",
                                "y": "-167.91720581054688",
                                "yaw": "91.41353607177734",
                                "z": "0.0"
                            }
                        },
                        {
                            "transform": {
                                "pitch": "0",
                                "x": -3.44,
                                "y": -167.82,
                                "yaw": 91.0,
                                "z": 1.0
                            }
                        },
                        {
                            "transform": {
                                "pitch": "360.0",
                                "x": "0.15770983695983887",
                                "y": "-167.7312469482422",
                                "yaw": "91.41353607177734",
                                "z": "0.0"
                            }
                        },
                        {
                            "transform": {
                                "pitch": "359",
                                "x": 7.44,
                                "y": -163.66,
                                "yaw": 270.0,
                                "z": 1.0
                            }
                        },
                        {
                            "transform": {
                                "pitch": "0.0",
                                "x": "10.55854606628418",
                                "y": "-163.5830535888672",
                                "yaw": "-88.58646392822266",
                                "z": "0.0"
                            }
                        },
                        {
                            "transform": {
                                "pitch": "359",
                                "x": 10.99,
                                "y": -163.66,
                                "yaw": 270.0,
                                "z": 1.0
                            }
                        },
                        {
                            "transform": {
                                "pitch": "0.0",
                                "x": "7.061770915985107",
                                "y": "-163.75694274902344",
                                "yaw": "-88.58646392822266",
                                "z": "0.0"
                            }
                        },
                        {
                            "transform": {
                                "pitch": "359",
                                "x": 41.44,
                                "y": -203.9,
                                "yaw": 181.0,
                                "z": 1.0
                            }
                        },
                        {
                            "transform": {
                                "pitch": "0.0",
                                "x": "41.517005920410156",
                                "y": "-206.9641571044922",
                                "yaw": "-178.56045532226562",
                                "z": "0.0"
                            }
                        },
                        {
                            "transform": {
                                "pitch": "359",
                                "x": 25.77,
                                "y": -207.44,
                                "yaw": 181.0,
                                "z": 1.0
                            }
                        },
                        {
                            "transform": {
                                "pitch": "0.0",
                                "x": "25.680063247680664",
                                "y": "-203.86105346679688",
                                "yaw": "-178.56045532226562",
                                "z": "0.0"
                            }
                        },
                        {
                            "transform": {
                                "pitch": "359",
                                "x": -32.48,
                                "y": -198.25,
                                "yaw": 1.0,
                                "z": 1.0
                            }
                        },
                        {
                            "transform": {
                                "pitch": "360.0",
                                "x": "-32.566158294677734",
                                "y": "-194.82147216796875",
                                "yaw": "1.439544677734375",
                                "z": "0.0"
                            }
                        },
                        {
                            "transform": {
                                "pitch": "0",
                                "x": 239.39,
                                "y": 113.42,
                                "yaw": 270.0,
                                "z": 2.36
                            }
                        },
                        {
                            "transform": {
                                "pitch": "358.8267822265625",
                                "x": "242.86146545410156",
                                "y": "113.50442504882812",
                                "yaw": "271.3932189941406",
                                "z": "0.5679125189781189"
                            }
                        },
                        {
                            "transform": {
                                "pitch": "0",
                                "x": 232.36,
                                "y": 113.29,
                                "yaw": 90.0,
                                "z": 2.46
                            }
                        },
                        {
                            "transform": {
                                "pitch": "1.1732286214828491",
                                "x": "228.8646240234375",
                                "y": "113.20498657226562",
                                "yaw": "91.3932113647461",
                                "z": "0.5687512755393982"
                            }
                        },
                        {
                            "transform": {
                                "pitch": "359",
                                "x": -32.4,
                                "y": -194.71,
                                "yaw": 1.0,
                                "z": 1.0
                            }
                        },
                        {
                            "transform": {
                                "pitch": "360.0",
                                "x": "-32.30937957763672",
                                "y": "-198.31613159179688",
                                "yaw": "1.439544677734375",
                                "z": "0.0"
                            }
                        },
                        {
                            "transform": {
                                "pitch": "0",
                                "x": -44.77,
                                "y": 197.2,
                                "yaw": 187.0,
                                "z": 1.74
                            }
                        },
                        {
                            "transform": {
                                "pitch": "0",
                                "x": -84.6,
                                "y": 167.1,
                                "yaw": 78.0,
                                "z": 1.53
                            }
                        },
                        {
                            "transform": {
                                "pitch": "360.0",
                                "x": "-87.55733489990234",
                                "y": "167.6916961669922",
                                "yaw": "438.6856689453125",
                                "z": "0.0"
                            }
                        },
                        {
                            "transform": {
                                "pitch": "0",
                                "x": 52.91,
                                "y": 203.9,
                                "yaw": 0.0,
                                "z": 2.5
                            }
                        },
                        {
                            "transform": {
                                "pitch": "361.12353515625",
                                "x": "52.918731689453125",
                                "y": "207.39906311035156",
                                "yaw": "359.8570556640625",
                                "z": "0.2592363655567169"
                            }
                        },
                        {
                            "transform": {
                                "pitch": "0.0",
                                "x": "-73.64797973632812",
                                "y": "165.80230712890625",
                                "yaw": "257.414306640625",
                                "z": "0.0"
                            }
                        },
                        {
                            "transform": {
                                "pitch": "359",
                                "x": 99.49,
                                "y": -201.92,
                                "yaw": 184.0,
                                "z": 1.4
                            }
                        },
                        {
                            "transform": {
                                "pitch": "0.0",
                                "x": "99.58008575439453",
                                "y": "-205.50503540039062",
                                "yaw": "-178.56045532226562",
                                "z": "0.0"
                            }
                        },
                        {
                            "transform": {
                                "pitch": "359",
                                "x": 99.49,
                                "y": -205.37,
                                "yaw": 184.0,
                                "z": 1.4
                            }
                        },
                        {
                            "transform": {
                                "pitch": "0.0",
                                "x": "99.405517578125",
                                "y": "-202.00833129882812",
                                "yaw": "-178.56045532226562",
                                "z": "0.0"
                            }
                        },
                        {
                            "transform": {
                                "pitch": "359",
                                "x": 68.68,
                                "y": -195.79,
                                "yaw": 1.0,
                                "z": 1.4
                            }
                        },
                        {
                            "transform": {
                                "pitch": "360.0",
                                "x": "68.59178161621094",
                                "y": "-192.27935791015625",
                                "yaw": "1.439544677734375",
                                "z": "0.0"
                            }
                        },
                        {
                            "transform": {
                                "pitch": "359",
                                "x": 53.6,
                                "y": -192.29,
                                "yaw": 1.0,
                                "z": 1.4
                            }
                        },
                        {
                            "transform": {
                                "pitch": "360.0",
                                "x": "53.697120666503906",
                                "y": "-196.15476989746094",
                                "yaw": "1.439544677734375",
                                "z": "0.0"
                            }
                        },
                        {
                            "transform": {
                                "pitch": "350",
                                "x": 154.6,
                                "y": -164.4,
                                "yaw": 270.0,
                                "z": 4.7
                            }
                        },
                        {
                            "transform": {
                                "pitch": "0",
                                "x": 122.3,
                                "y": -190.88,
                                "yaw": 1.0,
                                "z": 1.21
                            }
                        },
                        {
                            "transform": {
                                "pitch": "360.0",
                                "x": "122.3891830444336",
                                "y": "-194.4285430908203",
                                "yaw": "1.439544677734375",
                                "z": "0.0"
                            }
                        },
                        {
                            "transform": {
                                "pitch": "11",
                                "x": 52.2,
                                "y": -133.34,
                                "yaw": 1.0,
                                "z": 6.48
                            }
                        },
                        {
                            "transform": {
                                "pitch": "16",
                                "x": 82.22,
                                "y": -166.54,
                                "yaw": 93.0,
                                "z": 5.3
                            }
                        },
                        {
                            "transform": {
                                "pitch": "0",
                                "x": 115.32,
                                "y": -135.69,
                                "yaw": 181.0,
                                "z": 9.0
                            }
                        },
                        {
                            "transform": {
                                "pitch": "0",
                                "x": 84.1,
                                "y": -103.48,
                                "yaw": 272.0,
                                "z": 9.0
                            }
                        },
                        {
                            "transform": {
                                "pitch": "0",
                                "x": 153.53,
                                "y": -100.37,
                                "yaw": 270.0,
                                "z": 9.0
                            }
                        },
                        {
                            "transform": {
                                "pitch": "12",
                                "x": 150.81,
                                "y": -165.57,
                                "yaw": 90.0,
                                "z": 4.4
                            }
                        },
                        {
                            "transform": {
                                "pitch": "0",
                                "x": 119.41,
                                "y": -132.31,
                                "yaw": 1.0,
                                "z": 9.0
                            }
                        },
                        {
                            "transform": {
                                "pitch": "0",
                                "x": 114.84,
                                "y": -76.55,
                                "yaw": 181.0,
                                "z": 9.0
                            }
                        },
                        {
                            "transform": {
                                "pitch": "0.0",
                                "x": "114.74317169189453",
                                "y": "-72.87480926513672",
                                "yaw": "-178.49090576171875",
                                "z": "8.0"
                            }
                        },
                        {
                            "transform": {
                                "pitch": "9",
                                "x": 82.9,
                                "y": -47.14,
                                "yaw": 270.0,
                                "z": 5.72
                            }
                        },
                        {
                            "transform": {
                                "pitch": "0",
                                "x": -117.14,
                                "y": 136.33,
                                "yaw": 359.0,
                                "z": 1.0
                            }
                        },
                        {
                            "transform": {
                                "pitch": "0",
                                "x": -77.96,
                                "y": 165.64,
                                "yaw": 269.0,
                                "z": 1.0
                            }
                        },
                        {
                            "transform": {
                                "pitch": "0.0",
                                "x": "-73.85211944580078",
                                "y": "164.83070373535156",
                                "yaw": "258.85479736328125",
                                "z": "0.0"
                            }
                        },
                        {
                            "transform": {
                                "pitch": "0",
                                "x": -74.43,
                                "y": 165.64,
                                "yaw": 269.0,
                                "z": 1.0
                            }
                        },
                        {
                            "transform": {
                                "pitch": "0.0",
                                "x": "-77.13905334472656",
                                "y": "166.22161865234375",
                                "yaw": "257.8827209472656",
                                "z": "0.0"
                            }
                        },
                        {
                            "transform": {
                                "pitch": "0",
                                "x": -84.59,
                                "y": 101.65,
                                "yaw": 89.0,
                                "z": 1.0
                            }
                        },
                        {
                            "transform": {
                                "pitch": "-1.012520670890808",
                                "x": "-88.08773803710938",
                                "y": "101.6595458984375",
                                "yaw": "89.84374237060547",
                                "z": "0.3357953727245331"
                            }
                        },
                        {
                            "transform": {
                                "pitch": "0",
                                "x": -88.12,
                                "y": 101.68,
                                "yaw": 89.0,
                                "z": 1.0
                            }
                        },
                        {
                            "transform": {
                                "pitch": "-1.012520670890808",
                                "x": "-84.58769989013672",
                                "y": "101.67036437988281",
                                "yaw": "89.84374237060547",
                                "z": "0.3354354798793793"
                            }
                        },
                        {
                            "transform": {
                                "pitch": "0",
                                "x": -45.5,
                                "y": 131.43,
                                "yaw": 178.0,
                                "z": 1.0
                            }
                        },
                        {
                            "transform": {
                                "pitch": "0",
                                "x": 2.9,
                                "y": 163.89,
                                "yaw": 270.0,
                                "z": 1.0
                            }
                        },
                        {
                            "transform": {
                                "pitch": "360.0",
                                "x": "5.693984508514404",
                                "y": "163.87232971191406",
                                "yaw": "269.637451171875",
                                "z": "0.0"
                            }
                        },
                        {
                            "transform": {
                                "pitch": "0",
                                "x": 5.6,
                                "y": 163.89,
                                "yaw": 270.0,
                                "z": 1.0
                            }
                        },
                        {
                            "transform": {
                                "pitch": "360.0",
                                "x": "2.194162607192993",
                                "y": "163.9115447998047",
                                "yaw": "269.637451171875",
                                "z": "0.0"
                            }
                        },
                        {
                            "transform": {
                                "pitch": "0",
                                "x": -6.12,
                                "y": 102.1,
                                "yaw": 89.0,
                                "z": 1.0
                            }
                        },
                        {
                            "transform": {
                                "pitch": "0.0",
                                "x": "-9.697037696838379",
                                "y": "102.12262725830078",
                                "yaw": "89.63746643066406",
                                "z": "0.0"
                            }
                        },
                        {
                            "transform": {
                                "pitch": "0",
                                "x": -9.62,
                                "y": 102.9,
                                "yaw": 89.0,
                                "z": 1.0
                            }
                        },
                        {
                            "transform": {
                                "pitch": "0.0",
                                "x": "-6.19218635559082",
                                "y": "102.87830352783203",
                                "yaw": "89.63746643066406",
                                "z": "0.0"
                            }
                        },
                        {
                            "transform": {
                                "pitch": "0",
                                "x": 34.39,
                                "y": 130.77,
                                "yaw": 179.0,
                                "z": 1.0
                            }
                        },
                        {
                            "transform": {
                                "pitch": "0",
                                "x": -37.43,
                                "y": 135.7,
                                "yaw": 358.0,
                                "z": 1.0
                            }
                        },
                        {
                            "transform": {
                                "pitch": "0",
                                "x": -145.53,
                                "y": 26.3,
                                "yaw": 269.0,
                                "z": 1.0
                            }
                        },
                        {
                            "transform": {
                                "pitch": "0",
                                "x": -116.7,
                                "y": -3.3,
                                "yaw": 180.0,
                                "z": 1.0
                            }
                        },
                        {
                            "transform": {
                                "pitch": "0",
                                "x": -149.26,
                                "y": -29.42,
                                "yaw": 90.0,
                                "z": 1.0
                            }
                        },
                        {
                            "transform": {
                                "pitch": "0",
                                "x": 170.37,
                                "y": 99.28,
                                "yaw": 270.0,
                                "z": 1.17
                            }
                        },
                        {
                            "transform": {
                                "pitch": "0",
                                "x": 139.75,
                                "y": 62.51,
                                "yaw": 359.0,
                                "z": 1.17
                            }
                        },
                        {
                            "transform": {
                                "pitch": "0",
                                "x": 201.12,
                                "y": 58.8,
                                "yaw": 178.0,
                                "z": 0.99
                            }
                        },
                        {
                            "transform": {
                                "pitch": "0",
                                "x": -77.8,
                                "y": 34.5,
                                "yaw": 269.0,
                                "z": 1.3
                            }
                        },
                        {
                            "transform": {
                                "pitch": "358.910400390625",
                                "x": "-74.27088165283203",
                                "y": "34.49037170410156",
                                "yaw": "269.84375",
                                "z": "0.18371541798114777"
                            }
                        },
                        {
                            "transform": {
                                "pitch": "0",
                                "x": -74.26,
                                "y": 31.95,
                                "yaw": 270.0,
                                "z": 1.3
                            }
                        },
                        {
                            "transform": {
                                "pitch": "359.0536804199219",
                                "x": "-77.77780151367188",
                                "y": "31.9595947265625",
                                "yaw": "269.84375",
                                "z": "0.13858206570148468"
                            }
                        },
                        {
                            "transform": {
                                "pitch": "0",
                                "x": -46.16,
                                "y": -2.92,
                                "yaw": 180.0,
                                "z": 1.3
                            }
                        },
                        {
                            "transform": {
                                "pitch": "0",
                                "x": -88.84,
                                "y": -28.87,
                                "yaw": 89.0,
                                "z": 1.3
                            }
                        },
                        {
                            "transform": {
                                "pitch": "0.8396051526069641",
                                "x": "-84.9437484741211",
                                "y": "-28.880624771118164",
                                "yaw": "89.84374237060547",
                                "z": "-0.26675039529800415"
                            }
                        },
                        {
                            "transform": {
                                "pitch": "0",
                                "x": -84.66,
                                "y": 69.48,
                                "yaw": 90.0,
                                "z": 2.62
                            }
                        },
                        {
                            "transform": {
                                "pitch": "-0.14853577315807343",
                                "x": "-88.17547607421875",
                                "y": "69.48959350585938",
                                "yaw": "89.84374237060547",
                                "z": "0.8320345282554626"
                            }
                        },
                        {
                            "transform": {
                                "pitch": "0",
                                "x": -77.7,
                                "y": 69.11,
                                "yaw": 270.0,
                                "z": 2.62
                            }
                        },
                        {
                            "transform": {
                                "pitch": "360.11688232421875",
                                "x": "-74.1764907836914",
                                "y": "69.10039520263672",
                                "yaw": "269.84375",
                                "z": "0.8328475952148438"
                            }
                        },
                        {
                            "transform": {
                                "pitch": "0",
                                "x": -85.2,
                                "y": -78.9,
                                "yaw": 90.0,
                                "z": 0.97
                            }
                        },
                        {
                            "transform": {
                                "pitch": "-0.23343351483345032",
                                "x": "-88.58015441894531",
                                "y": "-78.89077758789062",
                                "yaw": "89.84374237060547",
                                "z": "-0.8594440817832947"
                            }
                        },
                        {
                            "transform": {
                                "pitch": "0",
                                "x": -78.4,
                                "y": -78.46,
                                "yaw": 270.0,
                                "z": 0.96
                            }
                        },
                        {
                            "transform": {
                                "pitch": "360.2005920410156",
                                "x": "-74.5789566040039",
                                "y": "-78.47042846679688",
                                "yaw": "269.84375",
                                "z": "-0.8611809015274048"
                            }
                        },
                        {
                            "transform": {
                                "pitch": "0",
                                "x": 4.89,
                                "y": -78.46,
                                "yaw": 270.0,
                                "z": 1.81
                            }
                        },
                        {
                            "transform": {
                                "pitch": "0.0",
                                "x": "8.455883979797363",
                                "y": "-78.37200164794922",
                                "yaw": "-88.58646392822266",
                                "z": "0.0"
                            }
                        },
                        {
                            "transform": {
                                "pitch": "0",
                                "x": -6.34,
                                "y": 69.48,
                                "yaw": 90.0,
                                "z": 1.77
                            }
                        },
                        {
                            "transform": {
                                "pitch": "0.0",
                                "x": "-9.903441429138184",
                                "y": "69.50254821777344",
                                "yaw": "89.63746643066406",
                                "z": "0.0"
                            }
                        },
                        {
                            "transform": {
                                "pitch": "360.0",
                                "x": "5.094234466552734",
                                "y": "69.08776092529297",
                                "yaw": "269.637451171875",
                                "z": "0.0"
                            }
                        },
                        {
                            "transform": {
                                "pitch": "0",
                                "x": 52.91,
                                "y": 196.87,
                                "yaw": 179.0,
                                "z": 2.5
                            }
                        },
                        {
                            "transform": {
                                "pitch": "-1.1242796182632446",
                                "x": "52.90134048461914",
                                "y": "193.39906311035156",
                                "yaw": "179.85704040527344",
                                "z": "0.25958043336868286"
                            }
                        },
                        {
                            "transform": {
                                "pitch": "0",
                                "x": 235.35,
                                "y": -145.9,
                                "yaw": 91.0,
                                "z": 1.78
                            }
                        },
                        {
                            "transform": {
                                "pitch": "0.0",
                                "x": "238.2660675048828",
                                "y": "-146.11538696289062",
                                "yaw": "85.77556610107422",
                                "z": "0.0"
                            }
                        },
                        {
                            "transform": {
                                "pitch": "0",
                                "x": 236.45,
                                "y": -53.93,
                                "yaw": 91.0,
                                "z": 1.78
                            }
                        },
                        {
                            "transform": {
                                "pitch": "0.0",
                                "x": "232.93157958984375",
                                "y": "-54.01557540893555",
                                "yaw": "91.3932113647461",
                                "z": "0.0"
                            }
                        },
                        {
                            "transform": {
                                "pitch": "0",
                                "x": 244.44,
                                "y": 44.28,
                                "yaw": 271.0,
                                "z": 1.79
                            }
                        },
                        {
                            "transform": {
                                "pitch": "360.0",
                                "x": "241.04603576660156",
                                "y": "44.19745635986328",
                                "yaw": "271.3932189941406",
                                "z": "0.0"
                            }
                        },
                        {
                            "transform": {
                                "pitch": "0",
                                "x": 243.51,
                                "y": -54.21,
                                "yaw": 270.0,
                                "z": 1.79
                            }
                        },
                        {
                            "transform": {
                                "pitch": "360.0",
                                "x": "246.9384002685547",
                                "y": "-54.12661361694336",
                                "yaw": "271.3932189941406",
                                "z": "0.0"
                            }
                        },
                        {
                            "transform": {
                                "pitch": "0",
                                "x": 238.58,
                                "y": -144.85,
                                "yaw": 91.0,
                                "z": 1.83
                            }
                        },
                        {
                            "transform": {
                                "pitch": "0.0",
                                "x": "234.85678100585938",
                                "y": "-144.6316375732422",
                                "yaw": "86.64344024658203",
                                "z": "0.0"
                            }
                        },
                        {
                            "transform": {
                                "pitch": "1",
                                "x": 141.91,
                                "y": 203.68,
                                "yaw": 0.0,
                                "z": 4.1
                            }
                        },
                        {
                            "transform": {
                                "pitch": "361.2748107910156",
                                "x": "141.91873168945312",
                                "y": "207.17698669433594",
                                "yaw": "359.8570556640625",
                                "z": "2.23475980758667"
                            }
                        },
                        {
                            "transform": {
                                "pitch": "0",
                                "x": 245.35,
                                "y": -129.63,
                                "yaw": 270.0,
                                "z": 1.83
                            }
                        },
                        {
                            "transform": {
                                "pitch": "360.0",
                                "x": "248.77268981933594",
                                "y": "-129.54676818847656",
                                "yaw": "271.3932189941406",
                                "z": "0.0"
                            }
                        },
                        {
                            "transform": {
                                "pitch": "0",
                                "x": 185.95,
                                "y": -197.37,
                                "yaw": 0.0,
                                "z": 1.78
                            }
                        },
                        {
                            "transform": {
                                "pitch": "0.0",
                                "x": "185.9499969482422",
                                "y": "-193.89999389648438",
                                "yaw": "0.0",
                                "z": "0.0"
                            }
                        },
                        {
                            "transform": {
                                "pitch": "0",
                                "x": 230.94,
                                "y": -174.85,
                                "yaw": 65.0,
                                "z": 1.8
                            }
                        },
                        {
                            "transform": {
                                "pitch": "0.0",
                                "x": "227.7465362548828",
                                "y": "-173.4008331298828",
                                "yaw": "65.59180450439453",
                                "z": "0.0"
                            }
                        },
                        {
                            "transform": {
                                "pitch": "0",
                                "x": 237.1,
                                "y": -178.9,
                                "yaw": 245.0,
                                "z": 1.8
                            }
                        },
                        {
                            "transform": {
                                "pitch": "360.0",
                                "x": "240.00001525878906",
                                "y": "-180.2597198486328",
                                "yaw": "244.8795623779297",
                                "z": "0.0"
                            }
                        },
                        {
                            "transform": {
                                "pitch": "358",
                                "x": 160.88,
                                "y": 193.2,
                                "yaw": 179.0,
                                "z": 4.1
                            }
                        },
                        {
                            "transform": {
                                "pitch": "-1.260597586631775",
                                "x": "161.10287475585938",
                                "y": "196.4036102294922",
                                "yaw": "176.02037048339844",
                                "z": "2.6701090335845947"
                            }
                        },
                        {
                            "transform": {
                                "pitch": "0",
                                "x": 46.36,
                                "y": -203.4,
                                "yaw": 181.0,
                                "z": 1.8
                            }
                        },
                        {
                            "transform": {
                                "pitch": "0",
                                "x": 46.52,
                                "y": -196.33,
                                "yaw": 1.0,
                                "z": 1.8
                            }
                        },
                        {
                            "transform": {
                                "pitch": "360.0",
                                "x": "46.43220520019531",
                                "y": "-192.8362274169922",
                                "yaw": "1.439544677734375",
                                "z": "0.0"
                            }
                        },
                        {
                            "transform": {
                                "pitch": "0",
                                "x": 0.6,
                                "y": -163.36,
                                "yaw": 91.0,
                                "z": 1.82
                            }
                        },
                        {
                            "transform": {
                                "pitch": "360.0",
                                "x": "-3.4487547874450684",
                                "y": "-163.4599151611328",
                                "yaw": "91.41353607177734",
                                "z": "0.0"
                            }
                        },
                        {
                            "transform": {
                                "pitch": "358",
                                "x": 160.61,
                                "y": 196.49,
                                "yaw": 179.0,
                                "z": 4.1
                            }
                        },
                        {
                            "transform": {
                                "pitch": "-1.274809718132019",
                                "x": "160.38092041015625",
                                "y": "192.94418334960938",
                                "yaw": "176.3036651611328",
                                "z": "2.6584856510162354"
                            }
                        },
                        {
                            "transform": {
                                "pitch": "0",
                                "x": 240.99,
                                "y": 43.78,
                                "yaw": 271.0,
                                "z": 2.44
                            }
                        },
                        {
                            "transform": {
                                "pitch": "360.0",
                                "x": "244.55511474609375",
                                "y": "43.866703033447266",
                                "yaw": "271.3932189941406",
                                "z": "0.0"
                            }
                        },
                        {
                            "transform": {
                                "pitch": "0",
                                "x": 235.56,
                                "y": -37.12,
                                "yaw": 90.0,
                                "z": 1.8
                            }
                        },
                        {
                            "transform": {
                                "pitch": "0.0",
                                "x": "232.5224609375",
                                "y": "-37.193870544433594",
                                "yaw": "91.3932113647461",
                                "z": "0.0"
                            }
                        },
                        {
                            "transform": {
                                "pitch": "0",
                                "x": 231.92,
                                "y": -36.82,
                                "yaw": 90.0,
                                "z": 1.79
                            }
                        },
                        {
                            "transform": {
                                "pitch": "0.0",
                                "x": "236.01197814941406",
                                "y": "-36.72048568725586",
                                "yaw": "91.3932113647461",
                                "z": "0.0"
                            }
                        },
                        {
                            "transform": {
                                "pitch": "0",
                                "x": -37.73,
                                "y": 0.99,
                                "yaw": 7.0,
                                "z": 1.8
                            }
                        },
                        {
                            "transform": {
                                "pitch": "0",
                                "x": 32.76,
                                "y": -8.17,
                                "yaw": 180.0,
                                "z": 1.8
                            }
                        },
                        {
                            "transform": {
                                "pitch": "360.0",
                                "x": "32.66706466674805",
                                "y": "-4.5203680992126465",
                                "yaw": "181.4586181640625",
                                "z": "0.0"
                            }
                        },
                        {
                            "transform": {
                                "pitch": "0",
                                "x": 32.45,
                                "y": -4.56,
                                "yaw": 180.0,
                                "z": 1.8
                            }
                        },
                        {
                            "transform": {
                                "pitch": "360.0",
                                "x": "32.539730072021484",
                                "y": "-8.024791717529297",
                                "yaw": "181.48350524902344",
                                "z": "0.0"
                            }
                        },
                        {
                            "transform": {
                                "pitch": "0",
                                "x": -125.3,
                                "y": 45.81,
                                "yaw": 133.0,
                                "z": 0.99
                            }
                        },
                        {
                            "transform": {
                                "pitch": "0",
                                "x": -145.69,
                                "y": 92.34,
                                "yaw": 270.0,
                                "z": 0.99
                            }
                        },
                        {
                            "transform": {
                                "pitch": "0",
                                "x": -115.5,
                                "y": 30.75,
                                "yaw": 134.0,
                                "z": 0.99
                            }
                        },
                        {
                            "transform": {
                                "pitch": "0",
                                "x": -5.84,
                                "y": 170.34,
                                "yaw": 90.0,
                                "z": 1.0
                            }
                        },
                        {
                            "transform": {
                                "pitch": "0.0",
                                "x": "-9.265254020690918",
                                "y": "170.36167907714844",
                                "yaw": "89.63746643066406",
                                "z": "0.0"
                            }
                        },
                        {
                            "transform": {
                                "pitch": "0",
                                "x": -9.24,
                                "y": 170.42,
                                "yaw": 90.0,
                                "z": 1.0
                            }
                        },
                        {
                            "transform": {
                                "pitch": "0.0",
                                "x": "-5.764954566955566",
                                "y": "170.3980255126953",
                                "yaw": "89.63746643066406",
                                "z": "0.0"
                            }
                        },
                        {
                            "transform": {
                                "pitch": "0",
                                "x": 28.52,
                                "y": 196.65,
                                "yaw": 179.0,
                                "z": 1.0
                            }
                        },
                        {
                            "transform": {
                                "pitch": "-0.0878860130906105",
                                "x": "28.512041091918945",
                                "y": "193.4599151611328",
                                "yaw": "179.85704040527344",
                                "z": "0.0015862176660448313"
                            }
                        },
                        {
                            "transform": {
                                "pitch": "0",
                                "x": 28.72,
                                "y": 193.61,
                                "yaw": 179.0,
                                "z": 1.0
                            }
                        },
                        {
                            "transform": {
                                "pitch": "-0.09670676290988922",
                                "x": "28.72835350036621",
                                "y": "196.95938110351562",
                                "yaw": "179.85704040527344",
                                "z": "0.00192060018889606"
                            }
                        },
                        {
                            "transform": {
                                "pitch": "0",
                                "x": 110.65,
                                "y": -7.8,
                                "yaw": 180.0,
                                "z": 1.0
                            }
                        },
                        {
                            "transform": {
                                "pitch": "0.0",
                                "x": "110.58321380615234",
                                "y": "-3.3287293910980225",
                                "yaw": "-179.14419555664062",
                                "z": "0.0"
                            }
                        },
                        {
                            "transform": {
                                "pitch": "352",
                                "x": 77.66,
                                "y": -36.16,
                                "yaw": 91.0,
                                "z": 5.25
                            }
                        },
                        {
                            "transform": {
                                "pitch": "352",
                                "x": 148.52,
                                "y": -35.96,
                                "yaw": 91.0,
                                "z": 4.15
                            }
                        },
                        {
                            "transform": {
                                "pitch": "0",
                                "x": 182.48,
                                "y": -6.2,
                                "yaw": 180.0,
                                "z": 1.0
                            }
                        },
                        {
                            "transform": {
                                "pitch": "0.0",
                                "x": "182.4210662841797",
                                "y": "-2.2556450366973877",
                                "yaw": "-179.14419555664062",
                                "z": "0.0"
                            }
                        },
                        {
                            "transform": {
                                "pitch": "0",
                                "x": 199.72,
                                "y": 5.93,
                                "yaw": 0.0,
                                "z": 1.0
                            }
                        },
                        {
                            "transform": {
                                "pitch": "360.0",
                                "x": "199.66661071777344",
                                "y": "9.503244400024414",
                                "yaw": "0.855804443359375",
                                "z": "0.0"
                            }
                        },
                        {
                            "transform": {
                                "pitch": "0",
                                "x": 199.52,
                                "y": 9.7,
                                "yaw": 0.0,
                                "z": 0.99
                            }
                        },
                        {
                            "transform": {
                                "pitch": "360.0",
                                "x": "199.5752410888672",
                                "y": "6.001489639282227",
                                "yaw": "0.855804443359375",
                                "z": "0.0"
                            }
                        },
                        {
                            "transform": {
                                "pitch": "0",
                                "x": -34.45,
                                "y": 176.76,
                                "yaw": 144.0,
                                "z": 0.99
                            }
                        }
                    ],
                    "scenario_type": "Scenario1"
                },
                {
                    "available_event_configurations": [
                        {
                            "transform": {
                                "pitch": "0",
                                "x": 239.39,
                                "y": 113.42,
                                "yaw": 270.0,
                                "z": 2.36
                            }
                        },
                        {
                            "transform": {
                                "pitch": "358.8267822265625",
                                "x": "242.86146545410156",
                                "y": "113.50442504882812",
                                "yaw": "271.3932189941406",
                                "z": "0.5679125189781189"
                            }
                        },
                        {
                            "transform": {
                                "pitch": "0",
                                "x": 232.36,
                                "y": 113.29,
                                "yaw": 90.0,
                                "z": 2.46
                            }
                        },
                        {
                            "transform": {
                                "pitch": "1.1732286214828491",
                                "x": "228.8646240234375",
                                "y": "113.20498657226562",
                                "yaw": "91.3932113647461",
                                "z": "0.5687512755393982"
                            }
                        },
                        {
                            "transform": {
                                "pitch": "0",
                                "x": -84.6,
                                "y": 167.1,
                                "yaw": 78.0,
                                "z": 1.53
                            }
                        },
                        {
                            "transform": {
                                "pitch": "360.0",
                                "x": "-87.55733489990234",
                                "y": "167.6916961669922",
                                "yaw": "438.6856689453125",
                                "z": "0.0"
                            }
                        },
                        {
                            "transform": {
                                "pitch": "0",
                                "x": 52.91,
                                "y": 203.9,
                                "yaw": 0.0,
                                "z": 2.5
                            }
                        },
                        {
                            "transform": {
                                "pitch": "361.12353515625",
                                "x": "52.918731689453125",
                                "y": "207.39906311035156",
                                "yaw": "359.8570556640625",
                                "z": "0.2592363655567169"
                            }
                        },
                        {
                            "transform": {
                                "pitch": "0",
                                "x": -84.66,
                                "y": 69.48,
                                "yaw": 90.0,
                                "z": 2.62
                            }
                        },
                        {
                            "transform": {
                                "pitch": "-0.14853577315807343",
                                "x": "-88.17547607421875",
                                "y": "69.48959350585938",
                                "yaw": "89.84374237060547",
                                "z": "0.8320345282554626"
                            }
                        },
                        {
                            "transform": {
                                "pitch": "0",
                                "x": -77.7,
                                "y": 69.11,
                                "yaw": 270.0,
                                "z": 2.62
                            }
                        },
                        {
                            "transform": {
                                "pitch": "360.11688232421875",
                                "x": "-74.1764907836914",
                                "y": "69.10039520263672",
                                "yaw": "269.84375",
                                "z": "0.8328475952148438"
                            }
                        },
                        {
                            "transform": {
                                "pitch": "0",
                                "x": -85.2,
                                "y": -78.9,
                                "yaw": 90.0,
                                "z": 0.97
                            }
                        },
                        {
                            "transform": {
                                "pitch": "-0.23343351483345032",
                                "x": "-88.58015441894531",
                                "y": "-78.89077758789062",
                                "yaw": "89.84374237060547",
                                "z": "-0.8594440817832947"
                            }
                        },
                        {
                            "transform": {
                                "pitch": "0",
                                "x": -78.4,
                                "y": -78.46,
                                "yaw": 270.0,
                                "z": 0.96
                            }
                        },
                        {
                            "transform": {
                                "pitch": "360.2005920410156",
                                "x": "-74.5789566040039",
                                "y": "-78.47042846679688",
                                "yaw": "269.84375",
                                "z": "-0.8611809015274048"
                            }
                        },
                        {
                            "transform": {
                                "pitch": "0",
                                "x": 4.89,
                                "y": -78.46,
                                "yaw": 270.0,
                                "z": 1.81
                            }
                        },
                        {
                            "transform": {
                                "pitch": "0.0",
                                "x": "8.455883979797363",
                                "y": "-78.37200164794922",
                                "yaw": "-88.58646392822266",
                                "z": "0.0"
                            }
                        },
                        {
                            "transform": {
                                "pitch": "0",
                                "x": -6.34,
                                "y": 69.48,
                                "yaw": 90.0,
                                "z": 1.77
                            }
                        },
                        {
                            "transform": {
                                "pitch": "0.0",
                                "x": "-9.903441429138184",
                                "y": "69.50254821777344",
                                "yaw": "89.63746643066406",
                                "z": "0.0"
                            }
                        },
                        {
                            "transform": {
                                "pitch": "0",
                                "x": 52.91,
                                "y": 196.87,
                                "yaw": 179.0,
                                "z": 2.5
                            }
                        },
                        {
                            "transform": {
                                "pitch": "-1.1242796182632446",
                                "x": "52.90134048461914",
                                "y": "193.39906311035156",
                                "yaw": "179.85704040527344",
                                "z": "0.25958043336868286"
                            }
                        },
                        {
                            "transform": {
                                "pitch": "0",
                                "x": 235.35,
                                "y": -145.9,
                                "yaw": 91.0,
                                "z": 1.78
                            }
                        },
                        {
                            "transform": {
                                "pitch": "0.0",
                                "x": "238.2660675048828",
                                "y": "-146.11538696289062",
                                "yaw": "85.77556610107422",
                                "z": "0.0"
                            }
                        },
                        {
                            "transform": {
                                "pitch": "0",
                                "x": 236.45,
                                "y": -53.93,
                                "yaw": 91.0,
                                "z": 1.78
                            }
                        },
                        {
                            "transform": {
                                "pitch": "0.0",
                                "x": "232.93157958984375",
                                "y": "-54.01557540893555",
                                "yaw": "91.3932113647461",
                                "z": "0.0"
                            }
                        },
                        {
                            "transform": {
                                "pitch": "0",
                                "x": 243.51,
                                "y": -54.21,
                                "yaw": 270.0,
                                "z": 1.79
                            }
                        },
                        {
                            "transform": {
                                "pitch": "360.0",
                                "x": "246.9384002685547",
                                "y": "-54.12661361694336",
                                "yaw": "271.3932189941406",
                                "z": "0.0"
                            }
                        },
                        {
                            "transform": {
                                "pitch": "0",
                                "x": 238.58,
                                "y": -144.85,
                                "yaw": 91.0,
                                "z": 1.83
                            }
                        },
                        {
                            "transform": {
                                "pitch": "0.0",
                                "x": "234.85678100585938",
                                "y": "-144.6316375732422",
                                "yaw": "86.64344024658203",
                                "z": "0.0"
                            }
                        },
                        {
                            "transform": {
                                "pitch": "1",
                                "x": 141.91,
                                "y": 203.68,
                                "yaw": 0.0,
                                "z": 4.1
                            }
                        },
                        {
                            "transform": {
                                "pitch": "361.2748107910156",
                                "x": "141.91873168945312",
                                "y": "207.17698669433594",
                                "yaw": "359.8570556640625",
                                "z": "2.23475980758667"
                            }
                        },
                        {
                            "transform": {
                                "pitch": "0",
                                "x": 245.35,
                                "y": -129.63,
                                "yaw": 270.0,
                                "z": 1.83
                            }
                        },
                        {
                            "transform": {
                                "pitch": "360.0",
                                "x": "248.77268981933594",
                                "y": "-129.54676818847656",
                                "yaw": "271.3932189941406",
                                "z": "0.0"
                            }
                        },
                        {
                            "transform": {
                                "pitch": "0",
                                "x": 185.95,
                                "y": -197.37,
                                "yaw": 0.0,
                                "z": 1.78
                            }
                        },
                        {
                            "transform": {
                                "pitch": "0.0",
                                "x": "185.9499969482422",
                                "y": "-193.89999389648438",
                                "yaw": "0.0",
                                "z": "0.0"
                            }
                        },
                        {
                            "transform": {
                                "pitch": "0",
                                "x": 230.94,
                                "y": -174.85,
                                "yaw": 65.0,
                                "z": 1.8
                            }
                        },
                        {
                            "transform": {
                                "pitch": "0.0",
                                "x": "227.7465362548828",
                                "y": "-173.4008331298828",
                                "yaw": "65.59180450439453",
                                "z": "0.0"
                            }
                        },
                        {
                            "transform": {
                                "pitch": "0",
                                "x": 237.1,
                                "y": -178.9,
                                "yaw": 245.0,
                                "z": 1.8
                            }
                        },
                        {
                            "transform": {
                                "pitch": "360.0",
                                "x": "240.00001525878906",
                                "y": "-180.2597198486328",
                                "yaw": "244.8795623779297",
                                "z": "0.0"
                            }
                        },
                        {
                            "transform": {
                                "pitch": "358",
                                "x": 160.88,
                                "y": 193.2,
                                "yaw": 179.0,
                                "z": 4.1
                            }
                        },
                        {
                            "transform": {
                                "pitch": "-1.260597586631775",
                                "x": "161.10287475585938",
                                "y": "196.4036102294922",
                                "yaw": "176.02037048339844",
                                "z": "2.6701090335845947"
                            }
                        },
                        {
                            "transform": {
                                "pitch": "0",
                                "x": 46.36,
                                "y": -203.4,
                                "yaw": 181.0,
                                "z": 1.8
                            }
                        },
                        {
                            "transform": {
                                "pitch": "358",
                                "x": 160.61,
                                "y": 196.49,
                                "yaw": 179.0,
                                "z": 4.1
                            }
                        },
                        {
                            "transform": {
                                "pitch": "-1.274809718132019",
                                "x": "160.38092041015625",
                                "y": "192.94418334960938",
                                "yaw": "176.3036651611328",
                                "z": "2.6584856510162354"
                            }
                        },
                        {
                            "transform": {
                                "pitch": "0",
                                "x": 240.99,
                                "y": 43.78,
                                "yaw": 271.0,
                                "z": 2.44
                            }
                        }
                    ],
                    "scenario_type": "Scenario3"
                }
            ]
        }
    ]
}